async_logging/__init__.py
async_logging/config/__init__.py
async_logging/config/log_level_map.py
async_logging/config/logging_config.py
async_logging/config/stream_type.py
async_logging/models/__init__.py
async_logging/models/entry.py
async_logging/models/log.py
async_logging/models/log_level.py
async_logging/queue/__init__.py
async_logging/queue/consumer_status.py
async_logging/queue/log_consumer.py
async_logging/queue/log_provider.py
async_logging/queue/provider_status.py
async_logging/rotation/__init__.py
async_logging/rotation/file_size_parser.py
async_logging/rotation/time_parser.py
async_logging/snowflake/__init__.py
async_logging/snowflake/constants.py
async_logging/snowflake/snowflake.py
async_logging/snowflake/snowflake_generator.py
async_logging/streams/__init__.py
async_logging/streams/logger.py
async_logging/streams/logger_context.py
async_logging/streams/logger_stream.py
async_logging/streams/protocol.py
async_logging/streams/retention_policy.py
async_logging-0.3.8.dist-info/licenses/LICENSE
async_logging-0.3.8.dist-info/METADATA
async_logging-0.3.8.dist-info/WHEEL
async_logging-0.3.8.dist-info/top_level.txt
async_logging-0.3.8.dist-info/RECORD
