Metadata-Version: 2.4
Name: async-logging
Version: 0.3.8
Author-email: Ada Lundhe <corpheus91@gmail.com>
License: MIT License
Keywords: async,logging,python,distributed
Classifier: Development Status :: 3 - Alpha
Classifier: License :: OSI Approved :: MIT License
Classifier: Programming Language :: Python :: 3.11
Classifier: Programming Language :: Python :: 3.12
Classifier: Programming Language :: Python :: 3.13
Requires-Python: >=3.11
License-File: LICENSE
Requires-Dist: msgspec
Requires-Dist: zstandard
Dynamic: license-file
